pytpp/__init__.py
pytpp/__main__.py
pytpp/tpp_gui.py
pytpp/tpp_tools.py
pytpp/tpp_tools_regex.py
pytransit/DejaVuSans.ttf
pytransit/__init__.py
pytransit/__main__.py
pytransit/draw_trash.py
pytransit/fileDisplay.py
pytransit/file_system_py.py
pytransit/images.py
pytransit/norm_tools.py
pytransit/qcDisplay.py
pytransit/stat_tools.py
pytransit/tnseq_tools.py
pytransit/tnseq_tools_corrections.py
pytransit/transit_gui.py
pytransit/transit_tools.py
pytransit/trash.py
pytransit/view_trash.py
pytransit/analysis/CGI.py
pytransit/analysis/__init__.py
pytransit/analysis/anova.py
pytransit/analysis/base.py
pytransit/analysis/binomial.py
pytransit/analysis/corrplot.py
pytransit/analysis/essentiality.py
pytransit/analysis/example.py
pytransit/analysis/extract_GO_term_names.py
pytransit/analysis/extract_sanger.py
pytransit/analysis/gi.py
pytransit/analysis/griffin.py
pytransit/analysis/gumbel.py
pytransit/analysis/gumbel_mod.py
pytransit/analysis/gumbel_mod2.py
pytransit/analysis/gumbel_mod3.py
pytransit/analysis/gumbel_orig.py
pytransit/analysis/heatmap.py
pytransit/analysis/hmm.py
pytransit/analysis/norm.py
pytransit/analysis/normalize.py
pytransit/analysis/pathway_enrichment.py
pytransit/analysis/rankproduct.py
pytransit/analysis/resampling.py
pytransit/analysis/resampling_mod.py
pytransit/analysis/temp-gi.py
pytransit/analysis/temp.py
pytransit/analysis/temp1.py
pytransit/analysis/tn5gaps.py
pytransit/analysis/tnseq_stats.py
pytransit/analysis/ttnfitness.py
pytransit/analysis/utest.py
pytransit/analysis/zinb-interac.py
pytransit/analysis/zinb.py
pytransit/convert/__init__.py
pytransit/convert/base.py
pytransit/convert/gff_to_prot_table.py
pytransit/data/COG_roles.dat
pytransit/data/GO_associated_Rvs-3-11-18.txt
pytransit/data/GO_associated_Rvs.csv
pytransit/data/GO_term_names.dat
pytransit/data/GO_terms_for_each_Rv.obo-3-11-18.txt
pytransit/data/H37Rv.sanger_associated_RVS.csv
pytransit/data/H37Rv_COG_roles.dat
pytransit/data/H37Rv_GO_terms.txt
transit1-3.3.19.dist-info/LICENSE.md
transit1-3.3.19.dist-info/METADATA
transit1-3.3.19.dist-info/WHEEL
transit1-3.3.19.dist-info/entry_points.txt
transit1-3.3.19.dist-info/top_level.txt
transit1-3.3.19.dist-info/RECORD
