Metadata-Version: 2.1
Name: transit1
Version: 3.3.19
Summary: TRANSIT is a tool for the analysis of Tn-Seq data. It provides an easy to use graphical interface and access to three different analysis methods that allow the user to determine essentiality in a single condition as well as between conditions.
Home-page: https://github.com/mad-lab/transit
Author: Michael A. DeJesus
Author-email: mad@cs.tamu.edu
License: GNU GPL
Download-URL: https://github.com/mad-lab/transit
Keywords: tnseq,analysis,biology,genome
Platform: UNKNOWN
Classifier: Development Status :: 5 - Production/Stable
Classifier: Programming Language :: Python
Classifier: Programming Language :: Python :: 3
Classifier: Intended Audience :: Science/Research
Classifier: License :: OSI Approved :: GNU General Public License v3 (GPLv3)
Classifier: Operating System :: OS Independent
Classifier: Topic :: Scientific/Engineering :: Bio-Informatics
Requires-Python: >=3.6
License-File: LICENSE.md
Requires-Dist: wheel
Requires-Dist: setuptools
Requires-Dist: numpy (~=1.16)
Requires-Dist: scipy (~=1.2)
Requires-Dist: matplotlib (~=3.0)
Requires-Dist: pillow
Requires-Dist: scikit-learn
Requires-Dist: statsmodels (~=0.9)
Requires-Dist: pypubsub
Requires-Dist: wxPython
